{
  "monday": {
    "text": "New to Bitcoin? Start with the fundamentals — what Bitcoin actually is, explained in plain English 👇",
    "url": "https://easycryptomastery.com/what-is-bitcoin/"
  },
  "tuesday": {
    "text": "How does Bitcoin actually work behind the scenes? Here’s a simple, beginner-friendly explanation 👇",
    "url": "https://easycryptomastery.com/how-bitcoin-works-explained-simply/"
  },
  "wednesday": {
    "text": "Want the easiest long-term strategy for beginners? Dollar-Cost Averaging (DCA) explained simply 👇",
    "url": "https://easycryptomastery.com/dollar-cost-averaging/"
  },
  "thursday": {
    "text": "Before you buy anything: learn the 5 most important Bitcoin safety rules for beginners 👇",
    "url": "https://easycryptomastery.com/bitcoin-safety-for-beginners-5-things-you-must-know/"
  },
  "friday": {
    "text": "Bitcoin wallets confuse most beginners at first — here’s what a wallet actually is and how it works 👇",
    "url": "https://easycryptomastery.com/what-is-a-bitcoin-wallet-beginner-guide/"
  },
  "saturday": {
    "text": "Looking for beginner-friendly wallet options in 2025? Here are the best Bitcoin wallets (with simple pros/cons) 👇",
    "url": "https://easycryptomastery.com/best-bitcoin-wallets-for-beginners-2025/"
  },
  "sunday": {
    "text": "If you’re choosing an exchange for the first time, use this beginner-friendly comparison page before you sign up 👇",
    "url": "https://easycryptomastery.com/recommended-exchanges/"
  }
}
